[
  {
    "text":"City",
    "img":"/public/pdfs/city/1.jpg",
    "url":"/public/pdfs/city/city.pdf",
    "type":"topicItem",
    "caption":""
  },
  {
    "text":"City",
    "img":"/public/pdfs/city/2.jpg",
    "url":"/public/pdfs/city/city.pdf",
    "type":"topicItem",
    "caption":""
  },
  {
    "text":"City",
    "img":"/public/pdfs/city/3.jpg",
    "url":"/public/pdfs/city/city.pdf",
    "type":"topicItem",
    "caption":""
  },
  {
    "text":"City",
    "img":"/public/pdfs/city/4.jpg",
    "url":"/public/pdfs/city/city.pdf",
    "type":"topicItem",
    "caption":""
  },
  {
    "text":"City",
    "img":"/public/pdfs/city/5.jpg",
    "url":"/public/pdfs/city/city.pdf",
    "type":"topicItem",
    "caption":""
  }
]
